xconf/__init__.py
xconf/fs.py
xconf/contrib/__init__.py
xconf/vendor/__init__.py
xconf/vendor/py310_dataclasses.py
xconf/vendor/dacite/__init__.py
xconf/vendor/dacite/config.py
xconf/vendor/dacite/core.py
xconf/vendor/dacite/data.py
xconf/vendor/dacite/dataclasses.py
xconf/vendor/dacite/exceptions.py
xconf/vendor/dacite/py.typed
xconf/vendor/dacite/types.py
xconf-0.0.2.dist-info/LICENSE
xconf-0.0.2.dist-info/METADATA
xconf-0.0.2.dist-info/WHEEL
xconf-0.0.2.dist-info/top_level.txt
xconf-0.0.2.dist-info/RECORD
