Metadata-Version: 2.1
Name: xconf
Version: 0.0.2
Summary: Turns TOML files and command-line arguments into dataclasses for config
Author: Joseph D. Long
Author-email: jdl@zesty.space
License-File: LICENSE
Requires-Dist: toml >=0.10.2
Provides-Extra: all
Requires-Dist: fsspec ; extra == 'all'
Requires-Dist: pytest ; extra == 'all'
Requires-Dist: ray ; extra == 'all'
Provides-Extra: contrib
Requires-Dist: fsspec ; extra == 'contrib'
Requires-Dist: ray ; extra == 'contrib'
Provides-Extra: dev
Requires-Dist: pytest ; extra == 'dev'
